graphevo/__init__.py
graphevo/core.cpp
graphevo/core.cpython-313-darwin.so
graphevo/py.typed
graphevo-0.1.0.dist-info/licenses/LICENSE
graphevo-0.1.0.dist-info/METADATA
graphevo-0.1.0.dist-info/WHEEL
graphevo-0.1.0.dist-info/top_level.txt
graphevo-0.1.0.dist-info/RECORD
