Metadata-Version: 2.4
Name: graphevo
Version: 0.1.0
Summary: Genetic Algorithm for Graph Optimization
Home-page: https://github.com/Js-Hwang1/GraphEvo
Author: Junsung Hwang
Author-email: Junsung Hwang <hwang30916@gmail.com>
License-Expression: MIT
Project-URL: Homepage, https://github.com/Js-Hwang1/GraphEvo
Project-URL: Repository, https://github.com/Js-Hwang1/GraphEvo.git
Classifier: Programming Language :: Python :: 3
Classifier: Programming Language :: C++
Classifier: Operating System :: OS Independent
Classifier: Topic :: Scientific/Engineering :: Mathematics
Classifier: Topic :: Scientific/Engineering :: Artificial Intelligence
Requires-Python: >=3.7
License-File: LICENSE
Requires-Dist: numpy>=1.19.0
Requires-Dist: networkx>=2.5
Requires-Dist: scipy>=1.7.0
Requires-Dist: typing-extensions>=3.7.4
Provides-Extra: dev
Requires-Dist: pytest>=6.0; extra == "dev"
Requires-Dist: pytest-cov>=2.12; extra == "dev"
Requires-Dist: mypy>=0.910; extra == "dev"
Requires-Dist: black>=21.7b0; extra == "dev"
Requires-Dist: isort>=5.9.3; extra == "dev"
Requires-Dist: flake8>=3.9.2; extra == "dev"
Provides-Extra: docs
Requires-Dist: sphinx>=4.0; extra == "docs"
Requires-Dist: sphinx-rtd-theme>=0.5.2; extra == "docs"
Requires-Dist: numpydoc>=1.1.0; extra == "docs"
Dynamic: author
Dynamic: home-page
Dynamic: license-file
Dynamic: requires-python
